geg/__init__.py
geg/angular_resolution.py
geg/aspect_ratio.py
geg/crossing_angle.py
geg/edge_crossings.py
geg/edge_length_deviation.py
geg/edge_orthogonality.py
geg/gabriel_ratio.py
geg/geg_parser.py
geg/kruskal_stress.py
geg/neighbourhood_preservation.py
geg/node_resolution.py
geg/node_uniformity.py
geg/parse_graph.py
geg_metrics-0.1.8.dist-info/METADATA
geg_metrics-0.1.8.dist-info/WHEEL
geg_metrics-0.1.8.dist-info/RECORD
