Metadata-Version: 2.4
Name: geg-metrics
Version: 0.1.8
Summary: Graph drawing metrics and GEG parser
Project-URL: Homepage, https://gavjmooney.com/geg
Author: Gavin J. Mooney
License: MIT
Requires-Python: >=3.9
Requires-Dist: networkx>=2.8
Requires-Dist: numpy>=1.23
Requires-Dist: scikit-learn>=1.1
Requires-Dist: scipy>=1.9
Requires-Dist: svgpathtools>=1.6.1
